mongologger/__init__.py
mongologger/logger.py
mongologger-0.1.1.dist-info/METADATA
mongologger-0.1.1.dist-info/WHEEL
mongologger-0.1.1.dist-info/top_level.txt
mongologger-0.1.1.dist-info/RECORD
